Taipower/__init__.py
Taipower/api.py
Taipower/connection.py
Taipower/model.py
Taipower/utility.py
libtaipower-0.0.5.dist-info/LICENSE
libtaipower-0.0.5.dist-info/METADATA
libtaipower-0.0.5.dist-info/WHEEL
libtaipower-0.0.5.dist-info/top_level.txt
libtaipower-0.0.5.dist-info/RECORD
